autocut/__init__.py
autocut/__main__.py
autocut/cut.py
autocut/daemon.py
autocut/main.py
autocut/package_transcribe.py
autocut/transcribe.py
autocut/type.py
autocut/utils.py
autocut/whisper_model.py
autocut_sub-1.0.2.dist-info/LICENSE
autocut_sub-1.0.2.dist-info/METADATA
autocut_sub-1.0.2.dist-info/WHEEL
autocut_sub-1.0.2.dist-info/entry_points.txt
autocut_sub-1.0.2.dist-info/top_level.txt
autocut_sub-1.0.2.dist-info/RECORD
