Metadata-Version: 2.1
Name: autocut-sub
Version: 1.0.2
Summary: Cut video by subtitles
Home-page: https://github.com/mli/autocut
License: Apache License 2.0
Project-URL: source, https://github.com/mli/autocut
Classifier: License :: OSI Approved :: Apache Software License
Classifier: Operating System :: OS Independent
Classifier: Programming Language :: Python :: 3
Requires-Python: >=3.9
License-File: LICENSE
Requires-Dist: ffmpeg-python
Requires-Dist: moviepy
Requires-Dist: openai-whisper
Requires-Dist: opencc-python-reimplemented
Requires-Dist: parameterized
Requires-Dist: pydub
Requires-Dist: srt
Requires-Dist: torchaudio
Requires-Dist: tqdm
Provides-Extra: all
Requires-Dist: openai ; extra == 'all'
Requires-Dist: faster-whisper ; extra == 'all'
Provides-Extra: faster
Requires-Dist: faster-whisper ; extra == 'faster'
Provides-Extra: openai
Requires-Dist: openai ; extra == 'openai'
